androidx_2_androidy/__init__.py
androidx_2_androidy/convert_androidy.py
support_2_supporty/__init__.py
support_2_supporty/convert_supporty.py
convertsupporty-1.0.0.dist-info/LICENSE
convertsupporty-1.0.0.dist-info/METADATA
convertsupporty-1.0.0.dist-info/WHEEL
convertsupporty-1.0.0.dist-info/entry_points.txt
convertsupporty-1.0.0.dist-info/top_level.txt
convertsupporty-1.0.0.dist-info/RECORD
